TTLocVis/__init__.py
TTLocVis/module.py
TTLocVis-0.1.0.dist-info/LICENSE.txt
TTLocVis-0.1.0.dist-info/METADATA
TTLocVis-0.1.0.dist-info/WHEEL
TTLocVis-0.1.0.dist-info/dependency_links.txt
TTLocVis-0.1.0.dist-info/top_level.txt
TTLocVis-0.1.0.dist-info/RECORD
