Metadata-Version: 2.1
Name: TTLocVis
Version: 0.1.0
Summary: TTLocVis: A Twitter Topic Location Visualization package
Home-page: https://github.com/xillig/TTLocVis
Author: Gillian Kant, Christoph Weisser, Benjamin Saefken
Author-email: gilliankant@googlemail.com, c.weisser@stud.uni-goettingen.de, benjamin.saefken@uni-goettingen.de
Maintainer: Gillian Kant
Maintainer-email: gilliankant@googlemail.com
License: GNU GPLv3
Platform: UNKNOWN
Classifier: Development Status :: 4 - Beta
Classifier: Programming Language :: Python :: 3
Classifier: Programming Language :: Python :: 3.6
Classifier: Programming Language :: Python :: 3.7
Classifier: Programming Language :: Python :: 3.8
Classifier: License :: OSI Approved :: MIT License
Classifier: Operating System :: OS Independent
Requires-Python: >=3.6
Requires-Dist: pip (>=19.1.1)
Requires-Dist: gensim (>=3.8.1)
Requires-Dist: matplotlib (>=2.2.2)
Requires-Dist: numpy (==1.16.1)
Requires-Dist: pandas (==0.24.2)
Requires-Dist: pyproj (>=2.6.1.post1)
Requires-Dist: scikit-learn (>=0.21.2)
Requires-Dist: spacy (>=2.2.2)
Requires-Dist: tweepy (>=3.8.0)
Requires-Dist: urllib3 (>=1.25.8)
Requires-Dist: wordcloud (>=1.7.0)
